{
 "cells": [
  {
   "cell_type": "code",
   "execution_count": 1,
   "metadata": {},
   "outputs": [
    {
     "name": "stdout",
     "output_type": "stream",
     "text": [
      "a\n"
     ]
    }
   ],
   "source": [
    "print('a')"
   ]
  },
  {
   "cell_type": "code",
   "execution_count": 3,
   "metadata": {},
   "outputs": [],
   "source": [
    "from dis import dis"
   ]
  },
  {
   "cell_type": "code",
   "execution_count": 3,
   "metadata": {},
   "outputs": [
    {
     "data": {
      "text/plain": [
       "(1, 2, 3)"
      ]
     },
     "execution_count": 3,
     "metadata": {},
     "output_type": "execute_result"
    }
   ],
   "source": [
    "(1, 2, 3)"
   ]
  },
  {
   "cell_type": "code",
   "execution_count": 4,
   "metadata": {},
   "outputs": [
    {
     "data": {
      "text/plain": [
       "[1, 2, 3]"
      ]
     },
     "execution_count": 4,
     "metadata": {},
     "output_type": "execute_result"
    }
   ],
   "source": [
    "[1, 2, 3]"
   ]
  },
  {
   "cell_type": "code",
   "execution_count": 5,
   "metadata": {},
   "outputs": [
    {
     "name": "stdout",
     "output_type": "stream",
     "text": [
      "  0           0 RESUME                   0\n",
      "\n",
      "  1           2 RETURN_CONST             0 ((1, 2, 3, 'a'))\n"
     ]
    }
   ],
   "source": [
    "dis(compile('(1, 2, 3, \"a\")', 'string', 'eval'))"
   ]
  },
  {
   "cell_type": "code",
   "execution_count": 6,
   "metadata": {},
   "outputs": [
    {
     "name": "stdout",
     "output_type": "stream",
     "text": [
      "  0           0 RESUME                   0\n",
      "\n",
      "  1           2 BUILD_LIST               0\n",
      "              4 LOAD_CONST               0 ((1, 2, 3, 'a'))\n",
      "              6 LIST_EXTEND              1\n",
      "              8 RETURN_VALUE\n"
     ]
    }
   ],
   "source": [
    "dis(compile('[1, 2, 3, \"a\"]', 'string', 'eval'))"
   ]
  },
  {
   "cell_type": "code",
   "execution_count": 7,
   "metadata": {},
   "outputs": [
    {
     "name": "stdout",
     "output_type": "stream",
     "text": [
      "  0           0 RESUME                   0\n",
      "\n",
      "  1           2 LOAD_CONST               0 (1)\n",
      "              4 LOAD_CONST               1 (2)\n",
      "              6 LOAD_CONST               2 (3)\n",
      "              8 LOAD_CONST               3 (10)\n",
      "             10 LOAD_CONST               4 (20)\n",
      "             12 BUILD_LIST               2\n",
      "             14 BUILD_TUPLE              4\n",
      "             16 RETURN_VALUE\n"
     ]
    }
   ],
   "source": [
    "dis(compile('(1, 2, 3, [10, 20])', 'string', 'eval'))"
   ]
  },
  {
   "cell_type": "code",
   "execution_count": 14,
   "metadata": {},
   "outputs": [],
   "source": [
    "from timeit import timeit"
   ]
  },
  {
   "cell_type": "code",
   "execution_count": 9,
   "metadata": {},
   "outputs": [
    {
     "data": {
      "text/plain": [
       "0.16416120005305856"
      ]
     },
     "execution_count": 9,
     "metadata": {},
     "output_type": "execute_result"
    }
   ],
   "source": [
    "timeit(\"(1, 2, 3, 4, 5, 6, 7, 8, 9)\", number= 10_000_000)"
   ]
  },
  {
   "cell_type": "code",
   "execution_count": 10,
   "metadata": {},
   "outputs": [
    {
     "data": {
      "text/plain": [
       "0.8409038999816403"
      ]
     },
     "execution_count": 10,
     "metadata": {},
     "output_type": "execute_result"
    }
   ],
   "source": [
    "timeit(\"[1, 2, 3, 4, 5, 6, 7, 8, 9]\", number= 10_000_000)\n"
   ]
  },
  {
   "cell_type": "code",
   "execution_count": 1,
   "metadata": {},
   "outputs": [],
   "source": [
    "def fn1():\n",
    "    pass"
   ]
  },
  {
   "cell_type": "code",
   "execution_count": 4,
   "metadata": {},
   "outputs": [
    {
     "name": "stdout",
     "output_type": "stream",
     "text": [
      "  0           0 RESUME                   0\n",
      "\n",
      "  1           2 LOAD_NAME                0 (fn1)\n",
      "              4 LOAD_CONST               0 (10)\n",
      "              6 LOAD_CONST               1 (20)\n",
      "              8 BUILD_TUPLE              3\n",
      "             10 RETURN_VALUE\n"
     ]
    }
   ],
   "source": [
    "dis(compile('(fn1, 10, 20)', 'string', 'eval'))"
   ]
  },
  {
   "cell_type": "code",
   "execution_count": 5,
   "metadata": {},
   "outputs": [
    {
     "name": "stdout",
     "output_type": "stream",
     "text": [
      "  0           0 RESUME                   0\n",
      "\n",
      "  1           2 LOAD_CONST               0 (1)\n",
      "              4 LOAD_CONST               1 (2)\n",
      "              6 LOAD_CONST               2 (3)\n",
      "              8 LOAD_CONST               3 (10)\n",
      "             10 LOAD_CONST               4 (20)\n",
      "             12 BUILD_LIST               2\n",
      "             14 BUILD_LIST               4\n",
      "             16 RETURN_VALUE\n"
     ]
    }
   ],
   "source": [
    "dis(compile('[1, 2, 3, [10, 20]]', 'string', 'eval'))"
   ]
  },
  {
   "cell_type": "code",
   "execution_count": 6,
   "metadata": {},
   "outputs": [
    {
     "name": "stdout",
     "output_type": "stream",
     "text": [
      "  0           0 RESUME                   0\n",
      "\n",
      "  1           2 BUILD_LIST               0\n",
      "              4 LOAD_CONST               0 ((1, 2, 3, (10, 20)))\n",
      "              6 LIST_EXTEND              1\n",
      "              8 RETURN_VALUE\n"
     ]
    }
   ],
   "source": [
    "dis(compile('[1, 2, 3, (10, 20)]', 'string', 'eval'))\n"
   ]
  },
  {
   "cell_type": "code",
   "execution_count": 8,
   "metadata": {},
   "outputs": [],
   "source": [
    "l1 = [1, 2, 3, 4, 5, 6, 7, 8, 9]\n",
    "t1 = (1, 2, 3,4, 5, 6 ,7, 8, 9)"
   ]
  },
  {
   "cell_type": "code",
   "execution_count": 9,
   "metadata": {},
   "outputs": [
    {
     "data": {
      "text/plain": [
       "(1969363407616, 1969367077824)"
      ]
     },
     "execution_count": 9,
     "metadata": {},
     "output_type": "execute_result"
    }
   ],
   "source": [
    "id(l1), id(t1)"
   ]
  },
  {
   "cell_type": "code",
   "execution_count": 11,
   "metadata": {},
   "outputs": [
    {
     "data": {
      "text/plain": [
       "(1969363407616, 1969369603264)"
      ]
     },
     "execution_count": 11,
     "metadata": {},
     "output_type": "execute_result"
    }
   ],
   "source": [
    "l2 = list(l1)\n",
    "id(l1), id(l2)"
   ]
  },
  {
   "cell_type": "code",
   "execution_count": 12,
   "metadata": {},
   "outputs": [
    {
     "data": {
      "text/plain": [
       "(1969367077824, 1969367077824)"
      ]
     },
     "execution_count": 12,
     "metadata": {},
     "output_type": "execute_result"
    }
   ],
   "source": [
    "t2 = tuple(t1)\n",
    "id(t1), id(t2)"
   ]
  },
  {
   "cell_type": "code",
   "execution_count": 15,
   "metadata": {},
   "outputs": [
    {
     "data": {
      "text/plain": [
       "0.13907889999973122"
      ]
     },
     "execution_count": 15,
     "metadata": {},
     "output_type": "execute_result"
    }
   ],
   "source": [
    "timeit('tuple((1, 2, 3, 4, 5))', number=5_000_000)\n",
    "timeit('tuple((1, 2, 3, 4, 5))', number=5_000_000)"
   ]
  },
  {
   "cell_type": "code",
   "execution_count": 17,
   "metadata": {},
   "outputs": [],
   "source": [
    "import sys"
   ]
  },
  {
   "cell_type": "code",
   "execution_count": 18,
   "metadata": {},
   "outputs": [
    {
     "name": "stdout",
     "output_type": "stream",
     "text": [
      "1 items: 48\n",
      "2 items: 56\n",
      "3 items: 64\n",
      "4 items: 72\n",
      "5 items: 80\n",
      "6 items: 88\n",
      "7 items: 96\n",
      "8 items: 104\n",
      "9 items: 112\n",
      "10 items: 120\n"
     ]
    }
   ],
   "source": [
    "t = tuple()\n",
    "\n",
    "prev = sys.getsizeof(t)\n",
    "\n",
    "for i in range(10):\n",
    "    c = tuple(range(i + 1))\n",
    "    size_c = sys.getsizeof(c)\n",
    "    delta, prev = size_c - prev, size_c\n",
    "    print(f'{i + 1} items: {size_c}')"
   ]
  },
  {
   "cell_type": "code",
   "execution_count": 19,
   "metadata": {},
   "outputs": [
    {
     "name": "stdout",
     "output_type": "stream",
     "text": [
      "1 items: 72, delta = 16\n",
      "2 items: 72, delta = 0\n",
      "3 items: 88, delta = 16\n",
      "4 items: 88, delta = 0\n",
      "5 items: 104, delta = 16\n",
      "6 items: 104, delta = 0\n",
      "7 items: 120, delta = 16\n",
      "8 items: 120, delta = 0\n",
      "9 items: 136, delta = 16\n",
      "10 items: 136, delta = 0\n"
     ]
    }
   ],
   "source": [
    "l = list()\n",
    "\n",
    "prev = sys.getsizeof(l)\n",
    "\n",
    "for i in range(10):\n",
    "    c = list(range(i + 1))\n",
    "    size_c = sys.getsizeof(c)\n",
    "    delta, prev = size_c - prev, size_c\n",
    "    print(f'{i + 1} items: {size_c}, delta = {delta}')"
   ]
  },
  {
   "cell_type": "code",
   "execution_count": 20,
   "metadata": {},
   "outputs": [],
   "source": [
    "c = list()\n",
    "\n",
    "prev = sys.getsizeof(l)\n",
    "\n",
    "print(f'0 items: {prev}')\n",
    "for i in range(255):\n",
    "    c.append(i)\n",
    "    size_c = sys.getsizeof(c)\n",
    "    delta, prev = size_c - prev, size_c"
   ]
  },
  {
   "cell_type": "code",
   "execution_count": 24,
   "metadata": {},
   "outputs": [],
   "source": [
    "t = tuple(range(100_000))"
   ]
  },
  {
   "cell_type": "code",
   "execution_count": 25,
   "metadata": {},
   "outputs": [],
   "source": [
    "l = list(t)"
   ]
  },
  {
   "cell_type": "code",
   "execution_count": 26,
   "metadata": {},
   "outputs": [
    {
     "data": {
      "text/plain": [
       "0.25593499999376945"
      ]
     },
     "execution_count": 26,
     "metadata": {},
     "output_type": "execute_result"
    }
   ],
   "source": [
    "timeit('t[99_999]', globals = globals(), number = 10_000_000)  "
   ]
  },
  {
   "cell_type": "code",
   "execution_count": 27,
   "metadata": {},
   "outputs": [
    {
     "data": {
      "text/plain": [
       "0.42224060000444297"
      ]
     },
     "execution_count": 27,
     "metadata": {},
     "output_type": "execute_result"
    }
   ],
   "source": [
    "timeit('l[99_999]', globals = globals(), number = 10_000_000)  "
   ]
  },
  {
   "cell_type": "code",
   "execution_count": null,
   "metadata": {},
   "outputs": [],
   "source": []
  }
 ],
 "metadata": {
  "kernelspec": {
   "display_name": "Python 3",
   "language": "python",
   "name": "python3"
  },
  "language_info": {
   "codemirror_mode": {
    "name": "ipython",
    "version": 3
   },
   "file_extension": ".py",
   "mimetype": "text/x-python",
   "name": "python",
   "nbconvert_exporter": "python",
   "pygments_lexer": "ipython3",
   "version": "3.12.4"
  }
 },
 "nbformat": 4,
 "nbformat_minor": 2
}
